# 시퀀스



## 시퀀스 분류

#### 담을 수 있는 자료형에 따라

- 컨테이너
    - 서로 다른 자료형을 담을 수 있는 객체
    - ex. `list`, `tuple`, `collections.deque`
- 플랫
    - 한 개의 자료형만 담을 수 있는 객체 
    - ex. `str`, `bytes`, `bytearray`, `array.array`, `memoryview`

#### 변동 가능한가에 따라

- 가변
    - `list`, `bytearray`, `array.array`,
- 불변
    - `tuple`, `str`, `bytes`



## map, filter

리스트 컴프리핸션 외에 `map`, `filter` 조합을 이용하여 똑같이 구현할 수 있다.

```python
chars = "abcdefghijk"

# 리스트 컴프리핸션
code_list = [ord(s) for c in chars if ord(s) > 10]

# list + filter + map
code_list = list(filter(lambda x: x > 40, map(ord, chars)))
```



## 제너레이터

메모리 할당을 한 번에 해버리는 `list` 와 다르게, 제너레이터는 실제 요소에 접근할 때만 메모리 할당을 한다.
즉 요소가 많은 시퀀스를 다룰 때, 훨씬 메모리 save 하게 사용할 수 있음.

```python
# 제너레이터 표현식 
code_list = (ord(s) for c in chars)

# next 함수를 사용하여 각 요소에 접근한다.
next(code_list)
next(code_list)
...
```



## 깊은 복사와 얕은 복사

파이썬은 기본적으로 할당이 참조의 개념(value by reference) 이다.
즉 복사도 기본적으로 얕은 복사다.

```python
>>> a = [1,2,3]
>>> b = a
>>> b[0] = 4
>>>
>>> a
[4, 2, 3]
>>> b
[4, 2, 3]
```

객체를 참조가 아닌 copy 해야 할 때는 `deepcopy` 패키지를 사용해야 한다.



## 그 외...

유용한 거만 적는당.

```python
>>> x, y, *z = range(10)
>>> x, y, z
(0, 1, [2, 3, 4, 5, 6, 7, 8, 9])
```



## hash

```python
t = (1, 2, 3)
l = [1, 2, 3]

print(hash(t))  # 234234123123
print(hash(l))  # error!
```

`hash` 는 불변(immutable) 타입에게만 사용할 수 있음

강의에 `setdefault` 에 대한 사용법이 나오지만, 실제로 쓰는 걸 한번도 본 적이 없어서 그냥 생략함.
(차라리 `defaultdict` 을 더 사용하는게 더 나을 듯.. 실제로 많이 사용하기도 하고)



## 읽기 전용 dictionary & set

```python
from types import MappingProxyType

d = {'key': 'value'}
d_frozen = MappingProxyType(d)  # 읽기 전용으로 만듬
```

```python
s = ('apple', 'orange')
s_frozen = frozenset(s)  # 읽기 전용으로 만듬
```



## 선언 최적화

`set([10, 12, 30])` 과 `{10, 12, 30}` 중 어떤게 더 최적화된 선언일까?
`dis` 모듈을 사용하면 내부적으로 어떤 순서를 거쳐 작동하는지 알 수 있다.

```python
from dis import dis

print(dis('set([10, 12, 30])'))
print('---------')
print(dis('{10, 12, 30}'))
```

```python
# output
  1           0 LOAD_NAME                0 (set)
              2 LOAD_CONST               0 (10)
              4 LOAD_CONST               1 (12)
              6 LOAD_CONST               2 (30)
              8 BUILD_LIST               3
             10 CALL_FUNCTION            1
             12 RETURN_VALUE
None
---------
  1           0 LOAD_CONST               0 (10)
              2 LOAD_CONST               1 (12)
              4 LOAD_CONST               2 (30)
              6 BUILD_SET                3
              8 RETURN_VALUE
```

딱 봐도 후자가 더 명령 스텝이 적은 것을 알 수 있다.



근데 전반적으로 시퀀스 내용이랑 별로 상관이 없네 ;;;